participation_coefficient.py
participation_coefficient-0.1.0.dist-info/METADATA
participation_coefficient-0.1.0.dist-info/WHEEL
participation_coefficient-0.1.0.dist-info/RECORD
